glide_for_redis-0.4.1.dist-info/METADATA
glide_for_redis-0.4.1.dist-info/WHEEL
glide/config.py
glide/protobuf_codec.py
glide/constants.py
glide/async_commands/sorted_set.py
glide/async_commands/transaction.py
glide/async_commands/__init__.py
glide/async_commands/core.py
glide/async_commands/standalone_commands.py
glide/async_commands/cluster_commands.py
glide/async_commands/redis_modules/json.py
glide/__init__.py
glide/glide.pyi
glide/logger.py
glide/redis_client.py
glide/py.typed
glide/exceptions.py
glide/protobuf/redis_request_pb2.py
glide/protobuf/redis_request_pb2.pyi
glide/protobuf/response_pb2.pyi
glide/protobuf/connection_request_pb2.pyi
glide/protobuf/connection_request_pb2.py
glide/protobuf/response_pb2.py
glide/routes.py
glide/glide.cpython-312-darwin.so
glide_for_redis-0.4.1.dist-info/RECORD
