Metadata-Version: 2.1
Name: glide-for-redis
Version: 0.4.1
Classifier: Development Status :: 4 - Beta
Classifier: Topic :: Database
Classifier: Topic :: Utilities
Classifier: License :: OSI Approved :: Apache Software License
Classifier: Intended Audience :: Developers
Classifier: Topic :: Software Development
Classifier: Programming Language :: Rust
Classifier: Programming Language :: Python :: Implementation :: CPython
Classifier: Programming Language :: Python :: Implementation :: PyPy
Requires-Dist: async-timeout>=4.0.2
Requires-Dist: typing-extensions>=4.8.0
Requires-Dist: google-api-python-client==2.85.0
Author: Amazon Web Services
License: Apache-2.0
Requires-Python: >=3.8
